{
  "whiskey": [
    {
      "name": "와일드 터키 101",
      "link": "https://img1.daumcdn.net/thumb/R1280x0/?scode=mtistory2&fname=https%3A%2F%2Fblog.kakaocdn.net%2Fdn%2FbR5K12%2FbtqDnxAs3gC%2FcrqJ94au9ryYl0D7tboVsK%2Fimg.jpg"
    },
    {
      "name": "조니워커 블랙라벨",
      "link": "https://cdn.veluga.kr/files/supplier/undefined/drinks/116.%E1%84%83%E1%85%B5%E1%84%8B%E1%85%A1%E1%84%8C%E1%85%B5%E1%84%8B%E1%85%A9%E1%84%8F%E1%85%A9%E1%84%85%E1%85%B5%E1%84%8B%E1%85%A1_%E1%84%8C%E1%85%A9%E1%84%82%E1%85%B5%E1%84%8B%E1%85%AF%E1%84%8F%E1%85%A5-%E1%84%87%E1%85%B3%E1%86%AF%E1%84%85%E1%85%A2%E1%86%A8-%E1%84%85%E1%85%A6%E1%84%8B%E1%85%B5%E1%84%87%E1%85%B3%E1%86%AF.png"
    },
    {
      "name": "조니워커 블루라벨",
      "link": "https://cdn.veluga.kr/files/supplier/undefined/drinks/117.%E1%84%83%E1%85%B5%E1%84%8B%E1%85%A1%E1%84%8C%E1%85%B5%E1%84%8B%E1%85%A9_%E1%84%8C%E1%85%A9%E1%84%82%E1%85%B5%E1%84%8B%E1%85%AF%E1%84%8F%E1%85%A5_%E1%84%87%E1%85%B3%E1%86%AF%E1%84%85%E1%85%AE_%E1%84%85%E1%85%A6%E1%84%8B%E1%85%B5%E1%84%87%E1%85%B3%E1%86%AF.png"
    },
    {
      "name": "라프로익 10년",
      "link": "https://cdn.wineroute.kr/base-product/base-product/78cb26d9-1af1-4c58-80c8-c1fa048767e2/41ce852d-8f7b-4bef-b2fa-5fde3e5ffdd0.jpg"
    },
    {
      "name": "글렌피딕 12년",
      "link": "https://eytzjvrxjleq11337293.cdn.ntruss.com/data/mall_data/images/product/00/00/00/16/13/m_0000001613.gif?1682574845"
    }
  ],
  "beer": [
    {
      "name": "사무엘 아담스",
      "link": "https://cdn.veluga.kr/drinks/0/main/59bd6455d6f54ed5aea867f92a2cd3b5_7c4aaf2f258d2e641bf5a5e08b569cc9.png"
    },
    {
      "name": "인디카 IPA",
      "link": "https://cdn.justwineapp.com/assets/beer/bottle/lost-coast-brewery-indica-ipa_1499190025.png"
    },
    {
      "name": "켈리",
      "link": "https://thumb.mt.co.kr/06/2023/03/2023033016162623786_2.jpg"
    },
    {
      "name": "파울라너 바이스비어",
      "link": "https://worldbeermarket.kr/userfiles/prdimg/2209280181_R.jpg"
    },
    {
      "name": "레페 브라운",
      "link": "https://assets.business.veluga.kr/media/public/%E1%84%85%E1%85%A6%E1%84%91%E1%85%A6_%E1%84%87%E1%85%B3%E1%84%85%E1%85%A1%E1%84%8B%E1%85%AE%E1%86%AB_%E1%84%87%E1%85%A7%E1%86%BC_1.png"
    }
  ]
}
